protoseq/__init__.py
protoseq/reader.py
protoseq/writer.py
hadoop_protoseq-0.0.1.dist-info/LICENSE
hadoop_protoseq-0.0.1.dist-info/METADATA
hadoop_protoseq-0.0.1.dist-info/WHEEL
hadoop_protoseq-0.0.1.dist-info/top_level.txt
hadoop_protoseq-0.0.1.dist-info/RECORD
