Metadata-Version: 2.1
Name: hadoop-protoseq
Version: 0.0.1
Summary: Python library for Hadoop Streaming with support of protobuf sequences
Home-page: https://github.com/vbugaevskii/hadoop-streaming-protoseq
Author: Bugaevskii Vladimir
Author-email: bugaevsky@mail.ru
License: MIT
Download-URL: https://github.com/vbugaevskii/hadoop-streaming-protoseq/archive/master.tar.gz
Keywords: hadoop,streaming,protobuf
Platform: UNKNOWN
Classifier: Environment :: Console
Classifier: Intended Audience :: Developers
Classifier: License :: OSI Approved :: MIT License
Classifier: Natural Language :: English
Classifier: Operating System :: POSIX :: Linux
Classifier: Programming Language :: Python :: 3
Classifier: Programming Language :: Python :: 3.7
Requires-Python: >=3.7
Requires-Dist: protobuf (>=3.11.0)
